airflowdaggenerator/__init__.py
airflowdaggenerator/__main__.py
airflowdaggenerator/airflowdaggenerator.py
airflowdaggenerator-0.0.2.dist-info/LICENSE
airflowdaggenerator-0.0.2.dist-info/METADATA
airflowdaggenerator-0.0.2.dist-info/WHEEL
airflowdaggenerator-0.0.2.dist-info/entry_points.txt
airflowdaggenerator-0.0.2.dist-info/top_level.txt
airflowdaggenerator-0.0.2.dist-info/RECORD
