Metadata-Version: 2.1
Name: airflowdaggenerator
Version: 0.0.2
Summary: Dynamically generates and validates Python Airflow DAG file based on a Jinja2 Template and a YAML configuration file to encourage code re-usability
Home-page: https://github.com/FelixKJose/AirflowDAGGenerator
Author: Felix K Jose
Author-email: felixkjose@gmail.com
License: Apache-2.0 License
Keywords: airflow,dynamic,dag,generator,jinja2
Platform: UNKNOWN
Classifier: Development Status :: 3 - Alpha
Classifier: Intended Audience :: Developers
Classifier: Natural Language :: English
Classifier: Programming Language :: Python :: 3
Classifier: Programming Language :: Python :: 3.6
Classifier: Programming Language :: Python :: 3.7
Classifier: Programming Language :: Python :: 3.8
Classifier: Operating System :: OS Independent
Requires-Python: >=3.6, <4
Requires-Dist: apache-airflow
Requires-Dist: psycopg2
Requires-Dist: PyYAML
Requires-Dist: jinja2 (<2.11.0,>=2.10.1)
